[
  {
    "market": "gas",
    "date": "2026-06-29",
    "area": "PEG",
    "product": null,
    "delivery": "202701",
    "price": 33.475
  },
  {
    "market": "gas",
    "date": "2026-06-30",
    "area": "PEG",
    "product": null,
    "delivery": "202701",
    "price": 33.827
  },
  {
    "market": "gas",
    "date": "2026-07-01",
    "area": "PEG",
    "product": null,
    "delivery": "202701",
    "price": 33.694
  },
  {
    "market": "gas",
    "date": "2026-06-29",
    "area": "PEG",
    "product": null,
    "delivery": "202801",
    "price": 26.382
  },
  {
    "market": "gas",
    "date": "2026-06-30",
    "area": "PEG",
    "product": null,
    "delivery": "202801",
    "price": 26.492
  },
  {
    "market": "gas",
    "date": "2026-07-01",
    "area": "PEG",
    "product": null,
    "delivery": "202801",
    "price": 26.405
  },
  {
    "market": "gas",
    "date": "2026-06-29",
    "area": "PEG",
    "product": null,
    "delivery": "202901",
    "price": 23.363
  },
  {
    "market": "gas",
    "date": "2026-06-30",
    "area": "PEG",
    "product": null,
    "delivery": "202901",
    "price": 23.363
  },
  {
    "market": "gas",
    "date": "2026-07-01",
    "area": "PEG",
    "product": null,
    "delivery": "202901",
    "price": 23.383
  },
  {
    "market": "gas",
    "date": "2026-06-29",
    "area": "PEG",
    "product": null,
    "delivery": "203001",
    "price": 21.65
  },
  {
    "market": "gas",
    "date": "2026-06-30",
    "area": "PEG",
    "product": null,
    "delivery": "203001",
    "price": 21.625
  },
  {
    "market": "gas",
    "date": "2026-07-01",
    "area": "PEG",
    "product": null,
    "delivery": "203001",
    "price": 21.475
  },
  {
    "market": "power",
    "date": "2026-06-29",
    "area": "FR",
    "product": "Base",
    "delivery": "202701",
    "price": 56.32
  },
  {
    "market": "power",
    "date": "2026-06-30",
    "area": "FR",
    "product": "Base",
    "delivery": "202701",
    "price": 57.39
  },
  {
    "market": "power",
    "date": "2026-07-01",
    "area": "FR",
    "product": "Base",
    "delivery": "202701",
    "price": 56.89
  },
  {
    "market": "power",
    "date": "2026-06-29",
    "area": "FR",
    "product": "Peak",
    "delivery": "202701",
    "price": 60.88
  },
  {
    "market": "power",
    "date": "2026-06-30",
    "area": "FR",
    "product": "Peak",
    "delivery": "202701",
    "price": 61.35
  },
  {
    "market": "power",
    "date": "2026-07-01",
    "area": "FR",
    "product": "Peak",
    "delivery": "202701",
    "price": 61.37
  },
  {
    "market": "power",
    "date": "2026-06-29",
    "area": "FR",
    "product": "Base",
    "delivery": "202801",
    "price": 50.84
  },
  {
    "market": "power",
    "date": "2026-06-30",
    "area": "FR",
    "product": "Base",
    "delivery": "202801",
    "price": 51.24
  },
  {
    "market": "power",
    "date": "2026-07-01",
    "area": "FR",
    "product": "Base",
    "delivery": "202801",
    "price": 50.59
  },
  {
    "market": "power",
    "date": "2026-06-29",
    "area": "FR",
    "product": "Peak",
    "delivery": "202801",
    "price": 58.29
  },
  {
    "market": "power",
    "date": "2026-06-30",
    "area": "FR",
    "product": "Peak",
    "delivery": "202801",
    "price": 58.5
  },
  {
    "market": "power",
    "date": "2026-07-01",
    "area": "FR",
    "product": "Peak",
    "delivery": "202801",
    "price": 57.92
  },
  {
    "market": "power",
    "date": "2026-06-29",
    "area": "FR",
    "product": "Base",
    "delivery": "202901",
    "price": 53.76
  },
  {
    "market": "power",
    "date": "2026-06-30",
    "area": "FR",
    "product": "Base",
    "delivery": "202901",
    "price": 53.99
  },
  {
    "market": "power",
    "date": "2026-07-01",
    "area": "FR",
    "product": "Base",
    "delivery": "202901",
    "price": 53.47
  },
  {
    "market": "power",
    "date": "2026-06-29",
    "area": "FR",
    "product": "Peak",
    "delivery": "202901",
    "price": 62.1
  },
  {
    "market": "power",
    "date": "2026-06-30",
    "area": "FR",
    "product": "Peak",
    "delivery": "202901",
    "price": 62.17
  },
  {
    "market": "power",
    "date": "2026-07-01",
    "area": "FR",
    "product": "Peak",
    "delivery": "202901",
    "price": 61.78
  },
  {
    "market": "power",
    "date": "2026-06-29",
    "area": "FR",
    "product": "Base",
    "delivery": "203001",
    "price": 57.76
  },
  {
    "market": "power",
    "date": "2026-06-30",
    "area": "FR",
    "product": "Base",
    "delivery": "203001",
    "price": 58.08
  },
  {
    "market": "power",
    "date": "2026-07-01",
    "area": "FR",
    "product": "Base",
    "delivery": "203001",
    "price": 57.56
  },
  {
    "market": "power",
    "date": "2026-06-29",
    "area": "FR",
    "product": "Peak",
    "delivery": "203001",
    "price": 68.54
  },
  {
    "market": "power",
    "date": "2026-06-30",
    "area": "FR",
    "product": "Peak",
    "delivery": "203001",
    "price": 68.54
  },
  {
    "market": "power",
    "date": "2026-07-01",
    "area": "FR",
    "product": "Peak",
    "delivery": "203001",
    "price": 68.03
  }
]